sphinx_api_sidebar/__init__.py
sphinx_api_sidebar/sphinx_api_sidebar.py
sphinx_api_sidebar-0.3.2.dist-info/LICENSE
sphinx_api_sidebar-0.3.2.dist-info/METADATA
sphinx_api_sidebar-0.3.2.dist-info/WHEEL
sphinx_api_sidebar-0.3.2.dist-info/entry_points.txt
sphinx_api_sidebar-0.3.2.dist-info/top_level.txt
sphinx_api_sidebar-0.3.2.dist-info/RECORD
