Metadata-Version: 2.1
Name: sphinx-api-sidebar
Version: 0.3.2
Summary: Display any generated static API documentation in a sidebar
Home-page: https://github.com/Yihengxiong6/sphinx_api_sidebar
Author: Yiheng Xiong
Author-email: Yiheng Xiong <georgex8866@gmail.com>
License: MIT License
Classifier: License :: OSI Approved :: MIT License
Classifier: Programming Language :: Python :: 3
Classifier: Programming Language :: Python :: 3.6
Classifier: Programming Language :: Python :: 3.7
Classifier: Programming Language :: Python :: 3.8
Classifier: Programming Language :: Python :: 3.9
Classifier: Programming Language :: Python :: 3.10
License-File: LICENSE
Requires-Dist: sphinx >=2.1
Provides-Extra: dev
Requires-Dist: black ~=23.3.0 ; extra == 'dev'
Requires-Dist: isort ~=5.12.0 ; extra == 'dev'
